README.md
pyproject.toml
setup.cfg
setup.py
admix/__init__.py
admix/_logging.py
admix/utils.py
admix/version.py
admix/ancestry/__init__.py
admix/ancestry/_local.py
admix/ancestry/_wrapper.py
admix/assoc/__init__.py
admix/assoc/_fast.py
admix/cli/__init__.py
admix/cli/_assoc.py
admix/cli/_ext.py
admix/cli/_genet_cor.py
admix/cli/_geno.py
admix/cli/_lanc.py
admix/cli/_plot.py
admix/cli/_simulate.py
admix/cli/_utils.py
admix/data/__init__.py
admix/data/_geno.py
admix/data/_lanc.py
admix/data/_misc.py
admix/data/_stats.py
admix/data/_utils.py
admix/dataset/__init__.py
admix/dataset/_dataset.py
admix/dataset/_index.py
admix/dataset/_load.py
admix/dataset/_utils.py
admix/estimate/__init__.py
admix/estimate/_admix_gen_cor.py
admix/estimate/_genetic_cor.py
admix/estimate/_utils.py
admix/estimate/_var_component.py
admix/io/__init__.py
admix/io/_read.py
admix/io/_write.py
admix/plot/__init__.py
admix/plot/_plot.py
admix/predict/__init__.py
admix/predict/_utils.py
admix/simulate/__init__.py
admix/simulate/_geno.py
admix/simulate/_lanc.py
admix/simulate/_pheno.py
admix/tools/__init__.py
admix/tools/_standalone.py
admix/tools/_utils.py
admix/tools/gcta.py
admix/tools/liftover.py
admix/tools/plink.py
admix/tools/plink2.py
admix_kit.egg-info/PKG-INFO
admix_kit.egg-info/SOURCES.txt
admix_kit.egg-info/dependency_links.txt
admix_kit.egg-info/entry_points.txt
admix_kit.egg-info/requires.txt
admix_kit.egg-info/top_level.txt