Metadata-Version: 2.1
Name: admix-kit
Version: 0.1.2
Summary: Tool kits for analyzing genetics data of admixed population
Home-page: https://github.com/kangchenghou/admix-kit
Author: Kangcheng Hou
Author-email: kangchenghou@gmail.com
Classifier: Programming Language :: Python :: 3
Classifier: Topic :: Scientific/Engineering :: Bio-Informatics
Classifier: Intended Audience :: Science/Research
Requires-Python: >=3.7
